README.md
setup.py
Small_fish/File_encryption.py
Small_fish/__init__.py
Small_fish/__main__.py
Small_fish/pack.py
Small_fish.egg-info/PKG-INFO
Small_fish.egg-info/SOURCES.txt
Small_fish.egg-info/dependency_links.txt
Small_fish.egg-info/entry_points.txt
Small_fish.egg-info/requires.txt
Small_fish.egg-info/top_level.txt
Small_fish/ENC/__init__.py
Small_fish/ENC/enc.py